
{
	"Cooldown":
	{
		"DESCRIPTION": "每打出或丢弃时，减少1层 #y冷却 层数，当 #y冷却 层数为0时，触发效果。",
		"NAMES": ["冷却"],
		"PROPER_NAME": "冷却"
	},
	"Martial Artist":
	{
		"DESCRIPTION": "#y同调 其他 #y武师 。",
		"NAMES": ["武师", "武师"],
		"PROPER_NAME": "武师"
	},
	"Motivate":
	{
		"DESCRIPTION": "随机减少手中1张牌直到被打出的1点耗能，重复 N 次。",
		"NAMES": ["激励"],
		"PROPER_NAME": "激励"
	},
	"~Orb Core":
	{
		"DESCRIPTION": "生成 1 个充能球。 NL NL 每回合第二次协同是获得一个额外效果。",
		"NAMES": ["~充能球核心", "~充能球核心"],
		"PROPER_NAME": "充能球核心"
	},
	"Reload":
	{
		"DESCRIPTION": "弃置若干牌，触发若干次。",
		"NAMES": ["重装填"],
		"PROPER_NAME": "重装填"
	},
	"Shapeshifter":
	{
		"DESCRIPTION": "与所有系列同调。",
		"NAMES": ["穿越者", "穿越"],
		"PROPER_NAME": "穿越者"
	},
	"Spellcaster":
	{
		"DESCRIPTION": "#y同调 其他 #y法师 。",
		"NAMES": ["法师"],
		"PROPER_NAME": "法师"
	},
	"Support Damage":
	{
		"DESCRIPTION": "每回合结束时，对血量最低的敌人造成伤害。受伤害调节影响。",
		"NAMES": ["支援伤害"],
		"PROPER_NAME": "支援伤害"
	},
	"Synergy":
	{
		"DESCRIPTION": "连续使用同一系列的牌或者 #y法师 或者 #y武师 时触发 #y同调 。",
		"NAMES": ["同调"],
		"PROPER_NAME": "同调"
	}
}
