
{
	"EYB:SelfDamagePower":
	{
		"DESCRIPTIONS": ["В конце хода, получит #b", " Урона."],
		"NAME": "Самоурон"
	},
	"EYB:MarkedPower":
	{
		"DESCRIPTIONS": ["Получит ещё #b{0} Урона от следующей #yАтаки."],
		"NAME": "Метка"
	},
	"EYB:ForcePower":
	{
		"DESCRIPTIONS": ["Потеряйте #b1 #yУсилие в начале хода.", " Если #b{0} #yУсилия, даёт #b{1} #yСилу."],
		"NAME": "Усилие"
	},
	"EYB:AgilityPower":
	{
		"DESCRIPTIONS": ["Потеряйте #b1 #yПроворство в начале хода.", " Если #b{0} #yПроворства, даёт #b{1} #yЛовкость."],
		"NAME": "Проворство"
	},
	"EYB:IntellectPower":
	{
		"DESCRIPTIONS": ["Потеряйте #b1 #yИнтеллект в начале хода.", " Если #b{0} #yИнтеллекта, даёт #b{1} #yФокус."],
		"NAME": "Интеллект"
	}
}