
{
	"EYB:ForceStance":
	{
		"NAME": "Force Stance",
		"DESCRIPTION": 
		[
			"#g+2 #yStrength, #r-1 #yFocus, #r-1 #yDexterity. NL On Enter: #yBoost #yForce. NL On Exit: <TODO>."
		]
	},
	"EYB:AgilityStance":
	{
		"NAME": "Agility Stance",
		"DESCRIPTION": 
		[
			"#g+2 #yDexterity, #r-1 #yStrength, #r-1 #yFocus. NL On Enter: #yBoost #yAgility. NL On Exit: <TODO>."
		]
	},
	"EYB:IntellectStance":
	{
		"NAME": "Intellect Stance",
		"DESCRIPTION": 
		[
			"#g+2 #yFocus, #g-1 #yStrength, #r-1 #yDexterity. NL On Enter: #yBoost #yIntellect. NL On Exit: <TODO>."
		]
	}
}