
{
	"BASIC":
	{
		"animator:Strike":
		{
			"DESCRIPTION": "",
			"NAME": "Strike"
		},
		"animator:Defend":
		{
			"DESCRIPTION": "",
			"NAME": "Defend"
		},
		
		"animator:Strike_Red":
		{
			"DESCRIPTION": "",
			"UPGRADE_DESCRIPTION": "!M! <R>: {~Retain} [F]",
			"NAME": "Improved Strike"
		},
		"animator:Defend_Red":
		{
			"DESCRIPTION": "",
			"UPGRADE_DESCRIPTION": "!M! <R>: {~Retain} [F]",
			"NAME": "Improved Defend"
		},
		
		"animator:Strike_Green":
		{
			"DESCRIPTION": "",
			"UPGRADE_DESCRIPTION": "!M! <G>: {~Retain} [A]",
			"NAME": "Improved Strike"
		},
		"animator:Defend_Green":
		{
			"DESCRIPTION": "",
			"UPGRADE_DESCRIPTION": "!M! <G>: {~Retain} [A]",
			"NAME": "Improved Defend"
		},
		
		"animator:Strike_Blue":
		{
			"DESCRIPTION": "",
			"UPGRADE_DESCRIPTION": "!M! <B>: {~Retain} [I]",
			"NAME": "Improved Strike"
		},
		"animator:Defend_Blue":
		{
			"DESCRIPTION": "",
			"UPGRADE_DESCRIPTION": "!M! <B>: {~Retain} [I]",
			"NAME": "Improved Defend"
		},
	
		"animator:Strike_Light":
		{
			"DESCRIPTION": "",
			"UPGRADE_DESCRIPTION": "!M! <L>: {~Retain} [B]",
			"NAME": "Improved Strike"
		},
		"animator:Defend_Light":
		{
			"DESCRIPTION": "",
			"UPGRADE_DESCRIPTION": "!M! <L>: {~Retain} [B]",
			"NAME": "Improved Defend"
		},
		
		"animator:Strike_Dark":
		{
			"DESCRIPTION": "",
			"UPGRADE_DESCRIPTION": "!M! <D>: {~Retain} [C]",
			"NAME": "Improved Strike"
		},
		"animator:Defend_Dark":
		{
			"DESCRIPTION": "",
			"UPGRADE_DESCRIPTION": "!M! <D>: {~Retain} [C]",
			"NAME": "Improved Defend"
		},
		
		"animator:Strike_Star":
		{
			"DESCRIPTION": "",
			"UPGRADE_DESCRIPTION": "Synergy: {~Retain} your ** highest {<W> Power}.",
			"NAME": "Improved Strike"
		},
		"animator:Defend_Star":
		{
			"DESCRIPTION": "",
			"UPGRADE_DESCRIPTION": "Synergy: {~Retain} your ** highest {<W> Power}.",
			"NAME": "Improved Defend"
		}
	},

	"BETA":
	{
		"animator:ManiwaHouou":
		{
			"DESCRIPTION": "",
			"NAME": "Maniwa Houou"
		}
	},

	"COLORLESS:RARE":
	{
		"animator:Emilia":
		{
			"DESCRIPTION": "Channel !M! [Frost]. || Next turn: Channel ** 1 Lightning for each ** Frost orb you have.",
			"NAME": "Emilia"
		},
		"animator:HarukoHaruhara":
		{
			"DESCRIPTION": "Discard a random card, ** then play a random card ** from your hand.",
			"NAME": "Haruko Haruhara"
		},
		"animator:Hibiki":
		{
			"DESCRIPTION": "Increase this card's ** number of hits by ** !S! this combat.",
			"NAME": "Hibiki"
		},
		"animator:HououinKyouma":
		{
			"DESCRIPTION": "Choose 1 card you ** played this combat. Add ** a copy of it to your ** hand and Retain it.",
			"NAME": "Hououin Kyouma"
		},
		"animator:Kira":
		{
			"DESCRIPTION": "Give the enemy !S! Strength. ** It will die after a certain ** number of turns. || This card's text will change ** while targeting an enemy.",
			"EXTENDED_DESCRIPTION": ["The enemy will die in !M! turn(s)."],
			"NAME": "Light Yagami"
		},
		"animator:KotoriKanbe":
		{
			"DESCRIPTION": "Fully heal the enemy. ** Apply 1 [Weak] and [Vulnerable] for ** every !M! HP healed. || <LIM>. If you healed {0} ** or more HP: The enemy ** also loses !S! Strength.",
			"NAME": "Kotori Kanbe"
		},
		"animator:Kyubey":
		{
			"DESCRIPTION": "Gain [E] [E]. ** <DRW-M>. || At the start of combat: ** Add 1 random Curse ** to your discard pile.",
			"NAME": "Kyubey"
		},
		"animator:Lelouch":
		{
			"DESCRIPTION": "Exhaust !M! random cards ** in hand. ALL enemies who ** are attacking will target ** themselves this turn, the ** others will be Stunned.",
			"NAME": "Lelouch"
		},
		"animator:Patchouli":
		{
			"DESCRIPTION": "Attack 1 additional time ** for each unique orb ** Channeled this combat. || <LIM>. At the start of ** combat, add a random {Orb} ** {Core} to your discard pile.",
			"NAME": "Patchouli"
		},
		"animator:TakanashiRikka":
		{
			"DESCRIPTION": "Create a 0-Cost ** copy of every {Attack} ** in your hand, they ** deal !M! damage and ** Purge on use.",
			"NAME": "Rikka Takanashi"
		},
		"animator:TanyaDegurechaff":
		{
			"DESCRIPTION": "Discard the top !S! {Skills} of your draw pile. <DRW-M>. || <LIM>. At the start of ** combat, add {Type 95} ** to your draw pile.",
			"NAME": "Tanya Degurechaff"
		}
	},

	"COLORLESS:UNCOMMON":
	{
		"animator:Canti":
		{
			"DESCRIPTION": "Deal additional ** damage equal to the ** enemy's current ** attack damage.",
			"NAME": "Canti"
		},
		"animator:Cirno":
		{
			"DESCRIPTION": "Apply !M! [Freezing] to ** ALL enemies. || When Exhausted, ** Channel 1 [Frost].",
			"NAME": "Cirno"
		},
		"animator:IchigoKurosaki":
		{
			"DESCRIPTION": "Boost [F] [A]. || When Exhausted: If you ** reached !S! [F] this combat, ** add {Ichigo Bankai} to ** your draw pile.",
			"NAME": "Ichigo Kurosaki",
			"UPGRADE_DESCRIPTION": "Boost [F] [A]. <DRW>. || When Exhausted: If you ** reached !S! [F] this combat, ** add {Ichigo Bankai} to ** your draw pile."
		},
		"animator:Kagari":
		{
			"DESCRIPTION": "Apply !M! [Shackles] ** to ALL enemies. || The next time ** you take damage: ** Channel !S! [Earth].",
			"EXTENDED_DESCRIPTION": ["The next #b{0} time(s) you take damage: Channel #b{1} [Earth]."],
			"NAME": "Kagari"
		},
		"animator:Kuroyukihime":
		{
			"DESCRIPTION": "Discard !M! cards to add ** {Black Lotus} to your ** hand, then Exhaust. || !A! <W>: Upgrade it.",
			"NAME": "Kuroyukihime"
		},
		"animator:LimeBell":
		{
			"DESCRIPTION": "Convert up ** to !M! [Block] into [Temp HP]. || Reload: Gain !S! [B].",
			"NAME": "Lime Bell"
		},
		"animator:Magilou":
		{
			"DESCRIPTION": "Trigger your first orb ** !M! time(s), then Evoke it. || <LIM>. When Drawn: ** Discard this and add ** {Bienfu} to your hand.",
			"NAME": "Magilou"
		},
		"animator:MamizouFutatsuiwa":
		{
			"DESCRIPTION": "Give a card LV2 <S>. || <LIM>. When Discarded: ** Create and add a random ** <S> card to your hand.",
			"EXTENDED_DESCRIPTION": ["turn into a Shapeshifter."],
			"NAME": "Mamizou Futatsuiwa"
		},
		"animator:MisaKurobane":
		{
			"DESCRIPTION": "<DRW-M>. ** Channel 1 [Fire]. || Add {Yusarin} to ** your discard pile.",
			"NAME": "Misa Kurobane"
		},
		"animator:MisakiNakahara":
		{
			"DESCRIPTION": "Choose and add 1 of !M! ** Colorless cards to ** your draw pile. || The first time you ** draw it: Motivate 1.",
			"NAME": "Misaki Nakahara"
		},
		"animator:NononJakuzure":
		{
			"DESCRIPTION": "Cycle !M! card(s). Motivate !S!. || Whenever you Synergize ** while this is in your hand: ** Increase this card's ** Motivate by 1.",
			"NAME": "Nonon Jakuzure"
		},
		"animator:QuestionMark":
		{
			"DESCRIPTION": "When drawn: Turns into ** a copy of a random card ** and gains Shapeshifter.",
			"NAME": "Question Mark",
			"UPGRADE_DESCRIPTION": "When drawn: Turns into ** an Upgraded copy of a ** random card and gains ** Shapeshifter."
		},
		"animator:Shimakaze":
		{
			"DESCRIPTION": "{~Retain} [A]. || <DRW-M>. ** Add 1 Dazed to ** your draw pile.",
			"NAME": "Shimakaze"
		},
		"animator:Rorona":
		{
			"DESCRIPTION": "Once per turn: ** Pay !S! [Gold] to obtain a ** random potion (Max 2). || At the end of combat: ** !M!% chance to permanently ** Upgrade a random card.",
			"EXTENDED_DESCRIPTION": ["Pay #b{0} [Gold] to obtain a random potion. || At the end of combat: #b{1}% chance to #yUpgrade a random card."],
			"NAME": "Rorona"
		},
		"animator:Urushihara":
		{
			"DESCRIPTION": "Channel 1 [Dark]. || Deal damage after a random number of turns.",
			"NAME": "Urushihara",
			"UPGRADE_DESCRIPTION": "Channel 1 [Dark]. || Deal damage after a random number of turns. || Slightly less {Lazy}."
		},
		"animator:Zero":
		{
			"DESCRIPTION": "Gain [I] || Play a random ** {Skill} from your ** draw pile.",
			"NAME": "Zero"
		}
	},

	"CURSE":
	{
		"animator:Curse_AscendersBane":
		{
			"DESCRIPTION": "Unplayable.",
			"EXTENDED_DESCRIPTION": ["Take !M! damage. || When Exhausted from ** the hand: Purge the top ** card of your draw pile. ** If it was a Hindrance: ** Replace it with this card.", "Ascension {0}+"],
			"NAME": "Ascender's Bane"
		},
		"animator:Curse_Dizziness":
		{
			"DESCRIPTION": "Unplayable. ** When drawn: Add ** a Dazed to your ** draw pile.",
			"NAME": "Dizziness"
		},
		"animator:Curse_Greed":
		{
			"DESCRIPTION": "Unplayable. ** When drawn: Raise ** the cost of a random ** card in your hand ** by 1 this turn.",
			"NAME": "Greed"
		},
		"animator:Curse_GriefSeed":
		{
			"DESCRIPTION": "At the end of turn: ** Take !M! Damage. || When Exhausted: ** Remove a random ** {Debuff}.",
			"NAME": "Grief Seed"
		},
		"animator:Curse_Nutcracker":
		{
			"DESCRIPTION": "Unplayable. ** At the end of turn: ** ALL enemies heal !M! HP.",
			"NAME": "Nutcracker"
		}
	},

	"SERIES:ELSWORD":
	{
		"animator:Add":
		{
			"DESCRIPTION": "Add !S! {Crystallize} to your ** draw pile. Next turn: Draw ** !M! card(s) and gain [E] [E]. || Synergy or !A! <D> : Exhaust a ** card anywhere, replace ** it with an {Orb Core}.",
			"NAME": "Add"
		},
		"animator:Ain":
		{
			"DESCRIPTION": "If you discarded ** a card this turn: ** Enter <IS>. || !S! <L>: Obtain {<B> Token}.",
			"NAME": "Ain"
		},
		"animator:Aisha":
		{
			"DESCRIPTION": "Deal !S! additional damage ** for each orb you have. || <LIM>. If you have 1 or ** more [Dark]: Gain {0} [I] [C].",
			"NAME": "Aisha"
		},
		"animator:Ara":
		{
			"DESCRIPTION": "<DRW> for every ** {Debuff} on the enemy. ** Discard 1 card. || !A! <R>: Apply !M! [Vulnerable].",
			"NAME": "Ara"
		},
		"animator:Chung":
		{
			"DESCRIPTION": "Decrease this card's ** [Block] by !M! this combat. || When Exhausted: ** Channel 1 [Frost].",
			"NAME": "Chung"
		},
		"animator:Ciel":
		{
			"DESCRIPTION": "Increase the damage of ** every copy of {Lu} by !M!. || !A! <B>: Apply {0} [~Lock-On]. || !A! <G>: Gain {1} [Blur].",
			"NAME": "Ciel"
		},
		"animator:Elesis":
		{
			"DESCRIPTION": "At the start of combat, ** choose 1 of 3 {Forms} and ** permanently change ** this card into it.",
			"EXTENDED_DESCRIPTION": ["Spend your remaining [E]: ** Gain twice that much [F] [A]. || When Drawn or Discarded: **  Increase this card's damage ** by !M! until played.", "Apply 1 [Burning] for every ** {Debuff} on the enemy. || <slm>. Synergy or ** Discard: <DRW>.", "Apply 1 [Vulnerable]. || At the start of each ** combat: Lose !M! HP."],
			"NAME": "Elesis"
		},
		"animator:Elsword":
		{
			"DESCRIPTION": "Cycle !M! card(s). || If the enemy ** has [Burning]: Motivate 1. ** Otherwise: Channel 1 [Fire].",
			"NAME": "Elsword"
		},
		"animator:Eve":
		{
			"DESCRIPTION": "When you Synergize: Deal damage equal to <W> to a random enemy !M! times. || Once per turn, pay 2 [E]: ** Play 1 of 3 {<W> Tokens}.",
			"EXTENDED_DESCRIPTION": ["Pay 2 [E] to play #b1 [A-Gen] #yToken. || Whenever a card #ySynergizes, deal damage equal to [A-Gen] to a random enemy #b{0} time(s)."],
			"NAME": "Eve"
		},
		"animator:Laby":
		{
			"DESCRIPTION": "Gain !S! [Enchanted Armor]. || At the start of each ** turn: Gain 1 [Constricted].",
			"EXTENDED_DESCRIPTION": ["At the start of each turn, gain #b{0} #yConstricted.", "At the start of each turn, gain #b{0} #yConstricted and apply #b{1} #yConstricted to ALL enemies."],
			"NAME": "Laby",
			"UPGRADE_DESCRIPTION": "Gain !S! [Enchanted Armor]. || At the start of each ** turn: Apply 1 [Constricted] to ** ALL characters."
		},
		"animator:Lu":
		{
			"DESCRIPTION": "Channel 1 [Dark] and [Frost]. || When Drawn: If ** in Neutral Stance, ** enter <FS>.",
			"NAME": "Lu"
		},
		"animator:Noah":
		{
			"DESCRIPTION": "Boost [C]. Apply !M! [Freezing]. || Less than !A! <D>: Take ** !S! damage at the ** end of turn.",
			"NAME": "Noah"
		},
		"animator:Raven":
		{
			"DESCRIPTION": "If the enemy is ** attacking: Apply 1 [Weak]. ** Otherwise: Apply 1 [Vulnerable]. || Next turn: <DRW>.",
			"NAME": "Raven"
		},
		"animator:Rena":
		{
			"DESCRIPTION": "Add 1 [T-Knife] to your hand. || <slm>. Synergy or ** Discard: Gain !S! [Blur].",
			"NAME": "Rena"
		}
	},

	"SERIES:FATE":
	{
		"animator:Alexander":
		{
			"DESCRIPTION": "{~Retain} [F]. || <FS>: Gain 1 [Plated Armor]. || When Exhausted: ** Play this card.",
			"NAME": "Alexander"
		},
		"animator:Archer":
		{
			"DESCRIPTION": "At the end of turn: Deal !M! ** damage to every enemy for ** each {Debuff} they have. || Synergy: Apply 1 [Vulnerable] ** to ALL enemies.",
			"NAME": "Archer"
		},
		"animator:Assassin":
		{
			"DESCRIPTION": "Can only be played ** if the enemy has !M! ** different {Debuffs}. || If you play an {Attack}: ** Cycle this card.",
			"NAME": "Assassin"
		},
		"animator:Berserker":
		{
			"DESCRIPTION": "Gain !M! [F]. || If the enemy dies or ** loses its [Block]: Gain !S! [Block]. || !A! <R>: Enter <FS>.",
			"NAME": "Berserker"
		},
		"animator:Caster":
		{
			"DESCRIPTION": "Channel 1 [Dark]. || Steal !M! Strength. || Gain !S! [Frail] and [C].",
			"EXTENDED_DESCRIPTION": ["Evoke your first orb.", "Apply {0} [Shackles].", "Gain [F] [I]."],
			"NAME": "Caster"
		},
		"animator:EmiyaShirou":
		{
			"DESCRIPTION": "Upgrade a random card ** in your hand !M! times. || If every card was ** already Upgraded: ** Draw 2 cards.",
			"NAME": "Emiya Shirou"
		},
		"animator:Gilgamesh":
		{
			"DESCRIPTION": "{~Unique}. Whenever you ** obtain a {Relic}, except ** by purchasing it: Gain ** !S! [Gold] and permanently ** Upgrade this card.",
			"NAME": "Gilgamesh"
		},
		"animator:Illya":
		{
			"DESCRIPTION": "Play the {Attack} with the ** highest damage from your ** draw pile. Take !M! damage ** at the end of turn. || When Exhausted: Draw ** {Berserker} from any ** pile and Retain it.",
			"NAME": "Illya"
		},
		"animator:Lancer":
		{
			"DESCRIPTION": "{~Retain} [A]. Apply 1 [Vulnerable]. || <slm>. For 2 turns: ** Increase the effect of [Vulnerable] ** on enemies by 25%.",
			"EXTENDED_DESCRIPTION": ["Enemies take {0}% more damage from [Vulnerable]."],
			"NAME": "Lancer"
		},
		"animator:Rider":
		{
			"DESCRIPTION": "Apply !M! [Shackles]. || !A! <G>: Boost [A]. || !A! <B>: Boost [I].",
			"NAME": "Rider"
		},
		"animator:RinTohsaka":
		{
			"DESCRIPTION": "Gain !S! {Temp}. [Artifact]. || <LIM>. !A! <R>, <G>, <B>: ** {Channel} !M! [Chaos].",
			"NAME": "Rin Tohsaka"
		},
		"animator:Saber":
		{
			"DESCRIPTION": "Cooldown !S! : Purge, then ** add {Excalibur} to your hand. || If this would enter your discard ** pile, move it to your draw pile. || Synergy: Reduce this card's ** Cooldown by an additional 2.",
			"NAME": "Saber"
		},
		"animator:SakuraMatou":
		{
			"DESCRIPTION": "90%Remove your strongest [Dark] ** to apply [Constricted] equal to half its ** damage. If you have no [Dark]: ** Channel 1 [Dark] and trigger its ** passive ability !M! times. || <LIM>. !A! <L>: Gain !S! [B].",
			"NAME": "Sakura Matou"
		},
		"animator:ShinjiMatou":
		{
			"DESCRIPTION": "Apply !M! [Poison] to ** a random enemy. || <slm>. On Synergy: ** Add a {Command Spell} to ** your hand and Retain it.",
			"NAME": "Shinji Matou"
		}
	},

	"SERIES:FULLMETALALCHEMIST":
	{
		"animator:ElricAlphonse":
		{
			"DESCRIPTION": "{~Retain} [I]. If you have ** !M! or less [I]: Gain [I]. || When Exhausted, add ** {Armored Alphonse} ** to your discard pile.",
			"NAME": "Alphonse Elric"
		},
		"animator:ElricEdward":
		{
			"DESCRIPTION": "Cycle 1 card. If it is a: || {Skill} -> Channel 1 [Frost]. ** {Attack} -> Channel 1 [Lightning]. ** {Power} -> Channel 1 [Earth].",
			"UPGRADE_DESCRIPTION": "<DESCRIPTION> ** {Hindrance} -> Channel 1 [Fire].",
			"NAME": "Edward Elric"
		},
		"animator:Envy":
		{
			"DESCRIPTION": "At the start of each turn: ** Upgrade the <W> levels ** of a random card. || Once per turn, pay 2 [E]: ** Gain 20% of your ** missing HP as [Temp HP].",
			"EXTENDED_DESCRIPTION": ["Pay 2 [E] to gain #b{0} [Temp HP]. || At the start of each turn: Increase the <W> levels of #b{1} random card(s) to LV2."],
			"NAME": "Envy"
		},
		"animator:Father":
		{
			"DESCRIPTION": "Lose !S!% of your Max HP. ** Obtain {Philosopher's Stone}. || Remove this card from ** your deck and from ** future card rewards.",
			"NAME": "Father"
		},
		"animator:Gluttony":
		{
			"DESCRIPTION": "Exhaust the top !M! cards ** of your draw pile to gain ** !M! [F] and Heal !M! HP. || Unplayable if you have less ** than !S! cards in play.",
			"EXTENDED_DESCRIPTION": ["Not enough cards in play."],
			"NAME": "Gluttony"
		},
		"animator:Greed":
		{
			"DESCRIPTION": "Choose !S!: Gain {0} [Block], ** Gain {1} [Temp HP], Gain {2} [Malleable], ** Gain {3} [Plated Armor], or Gain {4} [Metallicize]. || For every !M! [Gold] you have: Choose 1 additional effect.",
			"NAME": "Greed"
		},
		"animator:Lust":
		{
			"DESCRIPTION": "Attack 1 additional ** time for each ** Hindrance in hand. || If the enemy has [Vulnerable]: ** Gain !M! [Temp HP].",
			"NAME": "Lust"
		},
		"animator:MaesHughes":
		{
			"DESCRIPTION": "<DRW> for every !M! ** cards in your draw pile. ** Motivate 1. || When Exhausted: Draw {Roy ** Mustang} from any pile, it ** costs 1 less this turn.",
			"NAME": "Maes Hughes"
		},
		"animator:Pride":
		{
			"DESCRIPTION": "Channel !M! [Dark]. || Until next turn: [Dark] absorbs ** all unblocked damage you ** would take, and it applies ** !S! [Constricted] to the attacker.",
			"EXTENDED_DESCRIPTION": ["Your [Dark] absorbs all unblock damage, and it applies #b{0} [Constricted] to the attacker."],
			"NAME": "Pride"
		},
		"animator:RoyMustang":
		{
			"DESCRIPTION": "Channel 1 [Fire] ** for each enemy. || !A! <R>: Increase the ** damage bonus of [Burning] ** by !S!% this combat.",
			"NAME": "Roy Mustang"
		},
		"animator:Scar":
		{
			"DESCRIPTION": "Exhaust a card ** to Channel 1 [Earth]. || Synergy: Move a card ** from your Exhaust pile ** to your discard pile, ** then take !S! damage.",
			"EXTENDED_DESCRIPTION": ["Move a card to your discard pile, then take {0} damage."],
			"NAME": "Scar"
		},
		"animator:Sloth":
		{
			"DESCRIPTION": "Draw !M! less ** card(s) next turn. || When Exhausted: ** Gain !S! [Block].",
			"NAME": "Sloth"
		},
		"animator:WinryRockbell":
		{
			"DESCRIPTION": "Once per turn, ** when you discard a ** card: Gain !M! [Block]. || Pay [E]: Upgrade ** !S! random cards.",
			"EXTENDED_DESCRIPTION": ["Pay [E]: Upgrade {0} random cards. || The next #b{1} time(s) you discard a card this turn, gain #b{2} #yBlock."],
			"NAME": "Winry Rockbell"
		},
		"animator:Wrath":
		{
			"DESCRIPTION": "Gain !M! [F]. Give all cards ** in hand +1 [F] scaling. || If you have at least ** 7 cards in Exhaust pile: ** Obtain {<R> Token}.",
			"NAME": "Wrath"
		}
	},

	"SERIES:GATE":
	{
		"animator:Arpeggio":
		{
			"DESCRIPTION": "Gain !M! orb slot(s). || <B> Synergy bonus can ** be obtained 1 additional ** time each turn. || Pay 2 [E] to Channel 1 [Earth].",
			"EXTENDED_DESCRIPTION": ["Pay {0} [E] to Channel {1} [Earth]. || <B> Synergy bonus can be obtained {1} additional time(s) each turn."],
			"NAME": "Arpeggio"
		},
		"animator:Bozes":
		{
			"DESCRIPTION": "Motivate !M!. || Until end of turn, whenever a card Synergizes: Gain !S! [Support Damage].",
			"NAME": "Bozes"
		},
		"animator:CatoElAltestan":
		{
			"DESCRIPTION": "!A! <B>: Apply !M! [Freezing] || !A! <R>: Apply !S! [Burning] || !A! <G>: Channel 1 [Aether] || Fetch 2 <B> cards and ** give them +1 [I] scaling.",
			"NAME": "Cato El Altestan"
		},
		"animator:ItamiYouji":
		{
			"DESCRIPTION": "Attack 1 additional time ** for each card played ** this turn (max 10). || Synergy: Gain !S! [Support Damage].",
			"NAME": "Itami Youji"
		},
		"animator:MariKurokawa":
		{
			"DESCRIPTION": "Discard 2 {Attacks} ** to gain !S! Block. || Recover up to !M! of ** the HP you lost since the ** end of your last turn.",
			"NAME": "Kurokawa"
		},
		"animator:ShunyaKengun":
		{
			"DESCRIPTION": "Draw 1 <G> card ** and Retain it. || When drawn: Apply ** 1 [~Lock-On] to a random ** enemy, ignoring [Artifact].",
			"NAME": "Kengun"
		},
		"animator:Kuribayashi":
		{
			"DESCRIPTION": "Apply !M! [Vulnerable]. || !A! <G>: Attack twice. || !A! <R>: Apply !S! [Shackles].",
			"NAME": "Kuribayashi"
		},
		"animator:LeleiLaLalena":
		{
			"DESCRIPTION": "Discard a random card ** to {Channel} !M! [Frost]. || Synergy: Apply 1 [Weak].",
			"NAME": "Lelei La Lalena",
			"UPGRADE_DESCRIPTION": "Discard a card ** to {Channel} !M! [Frost]. || Synergy: Apply 1 [Weak]."
		},
		"animator:MoltSolAugustus":
		{
			"DESCRIPTION": "At the end of each turn: ** Give ALL <R> cards {~Haste}. || Draw 1 less card each turn. || Once per turn: Pay [E] to ** add !S! {Imperial Archers} ** to your draw pile.",
			"EXTENDED_DESCRIPTION": ["Once per turn: Pay [E] to add #b{0} #yImperial #yArchers to your draw pile. || Draw #b{1} less card(s) each turn. At the start of each turn: Give ALL <R> cards #yHaste."],
			"NAME": "Molt Sol Augustus"
		},
		"animator:PinaCoLada":
		{
			"DESCRIPTION": "Unplayable unless you ** Synergized this turn. || The first {0-Cost} card ** you play each turn is ** played twice.",
			"NAME": "Pina Co Lada"
		},
		"animator:RoryMercury":
		{
			"DESCRIPTION": "Give this card {~Haste}. || <slm>. If this hits an ** enemy with Vulnerable: ** Choose: Enter <FS>, ** or Enter <AS>.",
			"NAME": "Rory Mercury"
		},
		"animator:TukaLunaMarceau":
		{
			"DESCRIPTION": "If you have no [Block]: ** <DRW>. || !A! <L>: {~Retain} [B]. || !A! <G>: {~Retain} [A].",
			"NAME": "Tuka"
		},
		"animator:Tyuule":
		{
			"DESCRIPTION": "Increase the ** {Common Debuffs} of ** each enemy by 1. || X <D>, <B>: Apply !M! [Poison].",
			"NAME": "Tyuule"
		},
		"animator:YaoHaDucy":
		{
			"DESCRIPTION": "If the enemy intends ** to Attack: Apply !M! [Shackles]. || This card Synergizes ** with {0-Cost} cards.",
			"NAME": "Yao Ha Ducy"
		}
	},

	"SERIES:GOBLINSLAYER":
	{
		"animator:CowGirl":
		{
			"DESCRIPTION": "Fetch a {0-Cost} card from ** your draw pile. || <LIM>. When ** Discarded: Motivate 1.",
			"NAME": "Cow Girl",
			"UPGRADE_DESCRIPTION": "Fetch a {0-Cost} card from ** your draw or discard pile. || <LIM>. When ** Discarded: Motivate 1."
		},
		"animator:DwarfShaman":
		{
			"DESCRIPTION": "Channel 1 [Earth]. || <FS> or <IS>: ** <DRW>, then Upgrade 1 card.",
			"NAME": "Dwarf Shaman"
		},
		"animator:GoblinSlayer":
		{
			"DESCRIPTION": "Exhaust every Hindrance ** in hand and discard pile. || Deal 3 additional damage for every card in Exhaust pile. || {WARNING}: Goblins.",
			"NAME": "Goblin Slayer"
		},
		"animator:GuildGirl":
		{
			"DESCRIPTION": "At the start of turn: ** Cycle 1 card. || Whenever a non-minion ** enemy dies: Gain !M! [Gold]. ** Does not stack.",
			"NAME": "Guild Girl"
		},
		"animator:HighElfArcher":
		{
			"DESCRIPTION": "If you have !M! or ** less [A]: Gain [A]. || On Synergy: Give ** this card {~Haste}.",
			"NAME": "High Elf Archer"
		},
		"animator:LizardPriest":
		{
			"DESCRIPTION": "Retain !M! card(s) at ** the end of this turn. || Synergy: Set the [Block] ** of each enemy to 1.",
			"NAME": "Lizard Priest"
		},
		"animator:NobleFencer":
		{
			"DESCRIPTION": "Evoke your first [Lightning]. || Whenever you Synergize this turn: Channel 1 [Lightning].",
			"NAME": "Noble Fencer"
		},
		"animator:Priestess":
		{
			"DESCRIPTION": "Apply !S! [Weak]. || Synergy: Exhaust a ** random Hindrance ** from anywhere.",
			"NAME": "Priestess",
			"UPGRADE_DESCRIPTION": "Apply !S! [Weak] ** to ALL enemies. || Synergy: Exhaust a ** random Hindrance ** from anywhere."
		},
		"animator:Spearman":
		{
			"DESCRIPTION": "Boost [A] [F]. Add a ** {~Wound} to your draw pile. || <slm>. If you have ** {Witch} in hand: You may ** enter any Stance.",
			"NAME": "Spearman"
		},
		"animator:SwordMaiden":
		{
			"DESCRIPTION": "Remove your ** rightmost {Debuff}. || Boost [F] [A] [I].",
			"NAME": "Sword Maiden"
		},
		"animator:Witch":
		{
			"DESCRIPTION": "Apply !M! [Burning] ** to ALL enemies. || At the start of each ** {Elite} combat, obtain ** a random Potion.",
			"NAME": "Witch"
		}
	},

	"SERIES:HITSUGINOCHAIKA":
	{
		"animator:AcuraAkari":
		{
			"DESCRIPTION": "Discard 2 cards ** to obtain !M! [T-Knife]. || Synergy: Gain ** !S! {Temp}. Envenom.",
			"NAME": "Akari",
			"UPGRADE_DESCRIPTION": "Discard 2 cards to ** obtain !M! Upgraded [T-Knife]. || Synergy: Gain ** !S! {Temp}. Envenom."
		},
		"animator:AcuraShin":
		{
			"DESCRIPTION": "Apply !M! [Poison]. || Whenever you apply ** [Poison] this combat: ** Apply 1 more [Poison].",
			"NAME": "Shin"
		},
		"animator:AcuraTooru":
		{
			"DESCRIPTION": "Add !S! {Throwing-} ** {Knives} to your hand. || Synergy or Discard: ** Gain [A] and !M! [Block].",
			"NAME": "Tooru"
		},
		"animator:ChaikaBohdan":
		{
			"DESCRIPTION": "Whenever you hit an ** enemy while this is in ** your hand: Gain !S! ** damage until played.",
			"NAME": "Chaika Bohdan"
		},
		"animator:ChaikaTrabant":
		{
			"DESCRIPTION": "Played at the start of ** your next turn. ** Apply 1 [Weak] and [Vulnerable]. || When Discarded: Deal !M! ** damage to ALL enemies.",
			"NAME": "Chaika Trabant"
		},
		"animator:Fredrika":
		{
			"DESCRIPTION": "Gain !M! additional ** [Block] for each enemy. || When Discarded: Returns ** to your hand and changes ** Form until end of turn.",
			"EXTENDED_DESCRIPTION": ["", "Gain 2 [Metallicize].", "Apply 1 [Weak]. ** Apply 1 [Vulnerable]."],
			"NAME": "Fredrika"
		},
		"animator:Gillette":
		{
			"DESCRIPTION": "Next turn: Gain [E]. || When Discarded: ** Apply 1 [Weak] to ** ALL enemies.",
			"NAME": "Gillette"
		},
		"animator:Guy":
		{
			"DESCRIPTION": "<DRW-M>, then ** discard !M! card(s). || On Synergy: Discard ** the top 2 cards of ** your draw pile.",
			"NAME": "Guy"
		},
		"animator:Layla":
		{
			"DESCRIPTION": "Reload: Apply !M! [Poison] ** to a random enemy. || This card deals !S! ** more damage for each ** {Debuff} on the enemy.",
			"NAME": "Layla"
		},
		"animator:Viivi":
		{
			"DESCRIPTION": "<ST>. Gain [A] ** and <DRW>. || When Discarded: Add ** 1 [T-Knife] to your hand.",
			"NAME": "Viivi"
		}
	},

	"SERIES:KATANAGATARI":
	{
		"animator:Azekura":
		{
			"DESCRIPTION": "Gain !S! [Plated Armor]. Reduce ** the [Block] of all cards ** in your hand by !M!. || <FS> or when ** Exhausted: Gain !S! [Thorns].",
			"NAME": "Azekura"
		},
		"animator:Biyorigo":
		{
			"DESCRIPTION": "Gain 1 [Artifact] and !M! [Thorns]. || Once per turn, pay [E]: ** Gain 2 [F] and 2 [A].",
			"EXTENDED_DESCRIPTION": ["Pay #b1 [E] to gain #b{1} [F] [A]."],
			"NAME": "Biyorigo"
		},
		"animator:Emonzaemon":
		{
			"DESCRIPTION": "<LIM>. If this is your ** third attack in a row: ** Add {Entou Jyuu} to ** your draw pile.",
			"NAME": "Emonzaemon"
		},
		"animator:HigakiRinne":
		{
			"DESCRIPTION": "Behaves erratically...",
			"NAME": "Higaki Rinne",
			"UPGRADE_DESCRIPTION": "Behaves very ** erratically..."
		},
		"animator:Hitei":
		{
			"DESCRIPTION": "At the start of turn: ** Exhaust 1 of !S! random ** cards in draw or discard ** pile, then draw 1 card.",
			"NAME": "Hitei"
		},
		"animator:Konayuki":
		{
			"DESCRIPTION": "Gain !M! [F]. || <LIM>. !A! <R>: ** Deal !S! damage to ** a random enemy.",
			"NAME": "Konayuki"
		},
		"animator:Nanami":
		{
			"DESCRIPTION": "{Counter} the enemy intent. || This card will have a ** different text based on the ** enemy you are targeting. <SPACE>",
			"NAME": "Nanami",
			"UPGRADE_DESCRIPTION": "Strongly {Counter} ** the enemy intent. || This card will have a ** different text based on the ** enemy you are targeting."
		},
		"animator:Shichika":
		{
			"DESCRIPTION": "Gain/Boost [F] [A]. || Add {Kyotouryuu} ** to your hand.",
			"NAME": "Shichika"
		},
		"animator:Togame":
		{
			"DESCRIPTION": "<DRW-M>. ** You may Exhaust a card ** to draw 1 additional card. || <slm>. If you Exhausted ** a Hindrance: Motivate 1.",
			"NAME": "Togame"
		},
		"animator:TsurugaMeisai":
		{
			"DESCRIPTION": "Exhaust a card. Activate ** an effect based on its type: || {Power} -> Motivate 2. ** {Skill} -> Enter <AS>. ** {Attack} -> Add !M! copies of ** it to your draw pile.",
			"NAME": "Meisai"
		},
		"animator:UneriGinkaku":
		{
			"DESCRIPTION": "Unplayable if you ** {Attacked} this turn. || When Drawn: Gain ** !M! {Temp}. [Thorns].",
			"NAME": "Uneri Ginkaku"
		},
		"animator:ZankiKiguchi":
		{
			"DESCRIPTION": "<slm>. Re-Enter ** your current Stance. || When Exhausted: Move ** this card to your hand ** and give it Purge.",
			"NAME": "Zanki Kiguchi"
		}
	},

	"SERIES:KONOSUBA":
	{
		"animator:Aqua":
		{
			"DESCRIPTION": "Gain [B]. <DRW>. || Becomes useless for the ** rest of this combat.",
			"EXTENDED_DESCRIPTION": ["", "When Exhausted or ** Discarded: Gain !S! [Temp HP]."],
			"NAME": "Aqua",
			"UPGRADE_DESCRIPTION": "Boost [B]. <DRW>. || Becomes slightly less ** useless for the rest of ** this combat."
		},
		"animator:Chris":
		{
			"DESCRIPTION": "{~Steal} !M! [Gold]. || When Discarded: ** Draw a {0-Cost} card.",
			"NAME": "Chris"
		},
		"animator:Darkness":
		{
			"DESCRIPTION": "Gain !M! [Plated Armor]. || The next time you take ** damage: Add {Adrenaline} ** to your draw pile.",
			"NAME": "Darkness"
		},
		"animator:Eris":
		{
			"DESCRIPTION": "<LIM>. If you would die ** while this card is in hand, ** draw or discard pile, prevent ** all damage and remove this ** card from your deck.",
			"NAME": "Eris"
		},
		"animator:Hans":
		{
			"DESCRIPTION": "At the start of turn: ** Apply !M! [Poison] to ALL ** enemies, then gain ** !S! [Temp HP] for each ** enemy with [Poison].",
			"EXTENDED_DESCRIPTION": ["At the start of turn, apply #b{0} #y[Poison] to ALL enemies, then gain #b{1} #yTemporary #yHP for each enemy with #y[Poison]."],
			"NAME": "Hans"
		},
		"animator:Kazuma":
		{
			"DESCRIPTION": "Cycle 1 card. || Synergy: Gain !M! ** additional [Block].",
			"NAME": "Kazuma"
		},
		"animator:Megumin":
		{
			"DESCRIPTION": "{~Unique}. || <LIM>. On Synergy: ** Upgrade this card ** permanently.",
			"NAME": "Megumin"
		},
		"animator:Mitsurugi":
		{
			"DESCRIPTION": "Gain/Boost [F]. Can only ** deal damage if the ** enemy is attacking. || When Exhausted: ** Gain !S! [Block].",
			"NAME": "Mitsurugi"
		},
		"animator:Vanir":
		{
			"DESCRIPTION": "Decrease this card's ** damage by !M! this combat. || When Exhausted: Choose a ** card in draw pile and turn it ** into a new copy of this card.",
			"NAME": "Vanir"
		},
		"animator:Verdia":
		{
			"DESCRIPTION": "<DRW-M>. ** Apply !S! [Vulnerable]. || When Discarded: ** Gain 1 [Plated Armor].",
			"NAME": "Verdia"
		},
		"animator:Wiz":
		{
			"DESCRIPTION": "Exhaust 1 card. Choose a ** card in Exhaust pile and ** add a copy to your hand. || <LIM>. Synergy: This ** card will not Purge.",
			"NAME": "Wiz"
		},
		"animator:YunYun":
		{
			"DESCRIPTION": "Costs 1 more for each ** other {Attack} in hand. || <LIM>. When Drawn: ** {Channel} 1 [Lightning].",
			"NAME": "YunYun"
		}
	},
	
	"SERIES:LOGHORIZON":
	{
		"animator:Akatsuki":
		{
			"DESCRIPTION": "Deals !S! additional damage ** if the enemy is not attacking. || <slm>. When drawn: ** Create !M! {0-Cost} {0-Damage} ** copies of this card with ** {~Ethereal} and Purge.",
			"NAME": "Akatsuki"
		},
		"animator:Henrietta":
		{
			"DESCRIPTION": "Any Stance: Gain [E]. || At the end of each turn: ** Spend !S! of your ** remaining Energy to ** enter any Stance.",
			"EXTENDED_DESCRIPTION": ["At the end of each turn, spend 1 of your remaining Energy to enter any Stance."],
			"NAME": "Henrietta"
		},
		"animator:IsuzuTonan":
		{
			"DESCRIPTION": "For !M! turn(s): Whenever ** an {Attack} Synergizes, ** play a random lower ** cost {Attack} from ** your draw pile.",
			"EXTENDED_DESCRIPTION": ["For #b{0} turn(s), whenever an #yAttack #ySynergizes: Play a random lower cost #yAttack from your draw pile."],
			"NAME": "Isuzu Tonan"
		},
		"animator:KanamiAlt":
		{
			"DESCRIPTION": "Deals double damage ** to {Elites} and triple ** damage to {Bosses}. || If the enemy has [Vulnerable]: ** Gain [F][A] and !M! [Block].",
			"NAME": "Kanami"
		},
		"animator:Krusty":
		{
			"DESCRIPTION": "When drawn: {Autoplay}. || Increase this card [F] scaling by !M!.",
			"NAME": "Krusty"
		},
		"animator:Marielle":
		{
			"DESCRIPTION": "{Motivate} 1 card of each ** type in your draw pile. || Synergy: Gain !M! [Temp HP] ** and Purge.",
			"NAME": "Marielle"
		},
		"animator:HousakiMinori":
		{
			"DESCRIPTION": "Cooldown !S!: Gain !M! [Enchanted Armor]. || <SLM>. Synergy or ** Discard: Shuffle this card ** into your draw pile.",
			"NAME": "Minori Housaki"
		},
		"animator:HousakiTohya":
		{
			"DESCRIPTION": " Apply !M! [Vulnerable]. || Draw {Minori Housaki}. || !A! <W>: Gain [E]",
			"NAME": "Tohya Housaki"
		},
		"animator:Naotsugu":
		{
			"DESCRIPTION": "Play the lowest [Block] card ** with [Block] lower than ** unblocked damage dealt. || [F] Stance: Play ALL ** eligible cards instead.",
			"NAME": "Naotsugu"
		},
		"animator:Nyanta":
		{
			"DESCRIPTION": "Gain/Boost [A]. Apply a ** random {Common Debuff} ** on each attack. || Any Stance: Attack 1 ** additional time",
			"NAME": "Nyanta"
		},
		"animator:Rayneshia":
		{
			"DESCRIPTION": "<DRW-M>. Move !M! ** cards to your draw pile. || <LIM>. !A! <W>: ** Choose and add 1 of 3 {Rare} ** cards to your hand.",
			"NAME": "Rayneshia"
		},
		"animator:RundelhausCode":
		{
			"DESCRIPTION": "Gain [I]. Give !M! random ** card(s) +2 [I] scaling ** (does not stack). || !A! <W>: Choose 1: ** Channel [Fire], [Lightning] or [Frost].",
			"NAME": "Rundelhaus Code"
		},
		"animator:Serara":
		{
			"DESCRIPTION": "If an enemy intends ** to attack: Gain [F] and ** give a random card +2 [F] ** scaling (does not stack).",
			"NAME": "Serara",
			"UPGRADE_DESCRIPTION": "If an enemy intends ** to attack: Gain [F] and ** give a card +2 [F] ** scaling (does not stack)."
		},
		"animator:Shiroe":
		{
			"DESCRIPTION": "Cycle !M! cards. || All cards this turn have: 3 <W>: Apply !S! [Constricted] to ALL enemies.",
			"EXTENDED_DESCRIPTION": ["All cards have: <W> #b3: Apply #b{0} #yConstricted to ALL enemies."],
			"NAME": "Shiroe"
		},
		"animator:Soujiro":
		{
			"DESCRIPTION": "X <W>: Deal !M!X ** additional damage. || When drawn: Choose 1 of 4 ** cards to add to your hand, ** you can only choose the ** same card once.",
			"NAME": "Soujiro"
		},
		"animator:Tetora":
		{
			"DESCRIPTION": "Synergizes with {High ** Cost} cards. Requires ** !A! <W> to play. || Every third Synergy: ** Randomly gain [F], [A], [I].",
			"EXTENDED_DESCRIPTION": ["Every third #ySynergy, randomly gain #yForce, #yAgility or #yIntellect #b{0} time(s)."],
			"NAME": "Tetra"
		}
	},

	"SERIES:MADOKAMAGICA":
	{
		"animator:Charlotte":
		{
			"DESCRIPTION": "Apply !M! [Vulnerable] to ** ALL characters. || Unplayable unless you ** played a [Grief Seed] this turn.",
			"EXTENDED_DESCRIPTION": ["I have not played a Grief Seed this turn."],
			"NAME": "Charlotte"
		},
		"animator:HomuraAkemi":
		{
			"DESCRIPTION": "Skip the next enemy turn. ** Draw !M! card(s) and gain [E] ** next turn. End your turn. || Add !S! random {Curses} to ** your discard pile.",
			"NAME": "Homura Akemi"
		},
		"animator:IrohaTamaki":
		{
			"DESCRIPTION": "If the top card of ** your draw pile is a ** Hindrance: Exhaust it. || Synergy: Scry !M!.",
			"NAME": "Iroha Tamaki"
		},
		"animator:KyokoSakura":
		{
			"DESCRIPTION": "<ST>: Gain [F] ** and Channel 1 [Fire]. || <DRW-M>. ** Put !M! card(s) on top ** of your draw pile.",
			"NAME": "Kyoko Sakura"
		},
		"animator:MadokaKaname":
		{
			"DESCRIPTION": "Exhaust up to !M! random ** {Curses} from anywhere. ** Heal 3 HP for each (!S!). || While in hand: Gain 1 [Temp HP] ** when playing a Spellcaster.",
			"NAME": "Madoka Kaname"
		},
		"animator:MamiTomoe":
		{
			"DESCRIPTION": "Attack 1 additional ** time for each card pile ** which contains a [Grief Seed]. || When Drawn: Add a [Grief Seed] ** to your discard pile.",
			"NAME": "Mami Tomoe"
		},
		"animator:NagisaMomoe":
		{
			"DESCRIPTION": "Randomly Gain/Boost ** [A], [F] or [I] !M! times. || When Exhausted: Add ** {Charlotte} and a [Grief Seed] to ** your discard pile.",
			"NAME": "Nagisa Momoe"
		},
		"animator:Oktavia":
		{
			"DESCRIPTION": "Add !S! random {Curses} to ** your hand. Draw a card for ** each {Curse} in your hand. || Attacks once for each ** {Curse} in your hand.",
			"NAME": "Oktavia"
		},
		"animator:OrikoMikuni":
		{
			"DESCRIPTION": "Choose 1: Scry !M!, ** draw 1 card next turn, ** or gain !S! [Block] next turn. || <LIM>. <IS>: ** Choose all effects.",
			"NAME": "Oriko Mikuni"
		},
		"animator:SayakaMiki":
		{
			"DESCRIPTION": "Channel 1 [Frost]. || Lose no [I] next turn. || Synergy with [Grief Seed]: Add ** {Oktavia} and a [Grief Seed] to your ** discard pile, then Exhaust.",
			"NAME": "Sayaka Miki"
		},
		"animator:SuzuneAmano":
		{
			"DESCRIPTION": "<ST>: <DRW> and ** deal !S! additional damage ** for each [Fire] you have. || Exhaust 1 random ** card to apply !M! [Burning].",
			"NAME": "Suzune Amano",
			"UPGRADE_DESCRIPTION": "<ST>: <DRW> and ** deal !S! additional damage ** for each [Fire] you have. || Exhaust 1 card ** to apply !M! [Burning]."
		},
		"animator:YachiyoNanami":
		{
			"DESCRIPTION": "At the start of turn: ** you may discard a ** card to gain !M! Block. || Synergy: You may enter ** <AS> or <IS>.",
			"EXTENDED_DESCRIPTION": ["At the start of turn, you may discard up to #b{0} card(s) to gain #b{1} #yBlock each."],
			"NAME": "Yachiyo Nanami"
		},
		"animator:YuiTsuruno":
		{
			"DESCRIPTION": "Discard the bottom card ** of your draw pile. || When Exhausted or ** Discarded: Channel 1 [Fire] ** and add a [Grief Seed] to your hand.",
			"NAME": "Yui Tsuruno"
		}
	},

	"SERIES:NOGAMENOLIFE":
	{
		"animator:ChlammyZell":
		{
			"DESCRIPTION": "Draw 2 cards. Next turn, ** draw !M! additional card(s). || <LIM>. !A! <B> and <D>: Add ** a {Scheme} to your hand.",
			"NAME": "Kurami"
		},
		"animator:DolaCouronne":
		{
			"DESCRIPTION": "Discard !M! card(s). || <LIM>. When ** Exhausted: Gain ** !S! [Block] and 1 [Artifact].",
			"NAME": "Couronne"
		},
		"animator:DolaRiku":
		{
			"DESCRIPTION": "Exhaust a card in your hand, ** choose and obtain 1 of !M! cards ** of the same rarity, it costs 1 ** less this combat. || <SLM>. Synergy: ** Draw a {0-Cost} card.",
			"NAME": "Riku"
		},
		"animator:DolaSchwi":
		{
			"DESCRIPTION": "Channel [Lightning]. ** Apply !M! [~Lock-On]. || Cooldown !S! : Deal ** !D! {~Ranged} damage.",
			"NAME": "Schwi"
		},
		"animator:DolaStephanie":
		{
			"DESCRIPTION": "Choose a card in your ** hand: Fetch a card that ** would Synergize with it ** from your draw pile.",
			"EXTENDED_DESCRIPTION": ["Fetch Cards with the same Synergy."],
			"NAME": "Stephanie"
		},
		"animator:FielNirvalen":
		{
			"DESCRIPTION": "Choose and Boost ** !M! {Affinity Power(s)}. || Once per turn, when ** you shuffle your ** draw pile: Scry 2.",
			"EXTENDED_DESCRIPTION": ["Once per turn, when you shuffle your draw pile: #yScry #b{0}."],
			"NAME": "Fiel Nirvalen"
		},
		"animator:IzunaHatsuse":
		{
			"DESCRIPTION": "Apply 1 [Weak]. || While you are below ** 25% max HP, this card ** will change its form.",
			"EXTENDED_DESCRIPTION": [""],
			"NAME": "Izuna Hatsuse"
		},
		"animator:Jibril":
		{
			"DESCRIPTION": "Channel 1 [Dark]. ** Lose no [I] next turn. || On Synergy: Shuffle ** your orbs, then trigger ** your first !M! orbs.",
			"NAME": "Jibril"
		},
		"animator:Shiro":
		{
			"DESCRIPTION": "Costs 1 less for each time you ** Synergized this turn. At the ** start of each turn, gain [E] || Add {Sora} from your ** draw pile to your hand.",
			"NAME": "Shiro"
		},
		"animator:Sora":
		{
			"DESCRIPTION": "Choose 1 out of 3 ** random Effects !M! times. || Add {Shiro} from your ** draw pile to your hand.",
			"EXTENDED_DESCRIPTION": ["Attack", "Defend", "Prepare"],
			"NAME": "Sora"
		},
		"animator:Tet":
		{
			"DESCRIPTION": "Discard 1 card from ** your hand or draw pile. || Move 1 card from your ** discard pile to the top half ** of your draw pile.",
			"NAME": "Tet"
		}
	},

	"SERIES:ONEPUNCHMAN":
	{
		"animator:Boros":
		{
			"DESCRIPTION": "Every {Power} is ** played twice. || <LIM>. When ** Exhausted: Gain !M! ** Regeneration.",
			"NAME": "Boros"
		},
		"animator:Genos":
		{
			"DESCRIPTION": "Take !S! damage at ** the end of turn. || Synergy: Apply !M! [Burning].",
			"NAME": "Genos"
		},
		"animator:Geryuganshoop":
		{
			"DESCRIPTION": "Cycle !M! card(s). Purge ** up to !S! cards in Exhaust ** pile: Gain that much [E]. || <LIM>. If you Purged ** {Melzalgald} or {Boros}: ** Move them to your hand.",
			"EXTENDED_DESCRIPTION": ["Choose {0} cards to Purge, gain that much Energy."],
			"NAME": "Geryuganshoop"
		},
		"animator:Melzalgald":
		{
			"DESCRIPTION": "Add 3 {Attacks} to ** your hand and ** Retain them.",
			"NAME": "Melzalgald",
			"UPGRADE_DESCRIPTION": "Add 3 Upgraded ** {Attacks} to your hand ** and Retain them."
		},
		"animator:MetalKnight":
		{
			"DESCRIPTION": "Channel 1 [Plasma]. || Gain !M! [Metallicize], then ** decrease this number ** by 1 this combat.",
			"NAME": "Metal Knight"
		},
		"animator:MumenRider":
		{
			"DESCRIPTION": "When Exhausted: This ** card returns to your ** draw pile after a random ** number of turns.",
			"NAME": "Mumen Rider",
			"UPGRADE_DESCRIPTION": "<DRW>. || When Exhausted: This ** card returns to your ** draw pile after a random ** number of turns."
		},
		"animator:Saitama":
		{
			"DESCRIPTION": "Whenever this card is ** played, increase its cost ** and change its effect ** for this combat.",
			"EXTENDED_DESCRIPTION": ["<DRW-M>. ** Gain !S! [A].", "Prevent the next time ** you would lose HP.", "Gain !M! [F].", "", "Remove Intangible. ** Stun the enemy."],
			"NAME": "Saitama",
			"UPGRADE_DESCRIPTION": "Motivate 1. || Whenever this card is ** played, increase its cost ** and change its effect ** for this combat."
		},
		"animator:SilverFang":
		{
			"DESCRIPTION": "<AS>: Give a ** random {Attack} in ** your hand +1 [A] scaling. || Synergy: Enter <AS>.",
			"NAME": "Silver Fang"
		},
		"animator:Sonic":
		{
			"DESCRIPTION": "Gain !S! [A]. ** Gain !M! [Blur]. || Synergy: Add 1 [T-Knife] ** to your hand.",
			"NAME": "Sonic"
		},
		"animator:Tatsumaki":
		{
			"DESCRIPTION": "Channel 1 [Aether]. || <IS>: Gain 1 orb slot. || <slm>. If in Neutral ** Stance: Enter <IS>. ** Otherwise: Exit your Stance.",
			"NAME": "Tatsumaki"
		}
	},

	"SERIES:OVERLORD":
	{
		"animator:Ainz":
		{
			"DESCRIPTION": "At the start of turn: ** choose and execute 1 ** of 4 random {Effects}. || When Drawn: Decrease ** this card's cost by 1, then ** randomly gain [I], [F] or [A].",
			"NAME": "Ainz Ooal Gown"
		},
		"animator:Albedo":
		{
			"DESCRIPTION": "Gain [Enchanted Armor] equal ** to the damage dealt. || On Synergy: Gain 1 ** {Temporary} [Artifact].",
			"NAME": "Albedo"
		},
		"animator:Cocytus":
		{
			"DESCRIPTION": "If you have !M! or ** less [F]: Boost [F]. || <slm>. Synergy: ** Gain !S! [Plated Armor] and [Thorns].",
			"NAME": "Cocytus"
		},
		"animator:Demiurge":
		{
			"DESCRIPTION": "Gain [E]. ** Take !M! damage ** at the end of turn. || Synergy: Conserve ** your [E] next turn.",
			"NAME": "Demiurge",
			"UPGRADE_DESCRIPTION": "Gain [E]. Discard 1 ** card or take !M! damage ** at the end of turn. || Synergy: Conserve ** your [E] next turn."
		},
		"animator:Entoma":
		{
			"DESCRIPTION": "{~Unique}. Apply !M! [Poison]. ** Loses 1 damage each turn. || <LIM>. If this card kills an ** enemy: Gain 2 Max HP and ** Upgrade permanently.",
			"NAME": "Entoma"
		},
		"animator:Evileye":
		{
			"DESCRIPTION": "<DRW-M>. Reload: ** Trigger your next orb. || <LIM>. Synergy: Gain ** 2 [I] and 1 orb slot.",
			"NAME": "Evileye"
		},
		"animator:NarberalGamma":
		{
			"DESCRIPTION": "Channel !M! [Lightning]. || Lightning hits ALL ** enemies this turn.",
			"NAME": "Gamma Narberal",
			"UPGRADE_DESCRIPTION": "Channel !M! [Lightning]. ** <DRW>. || Lightning hits ALL ** enemies this turn."
		},
		"animator:PandorasActor":
		{
			"DESCRIPTION": "At the start of combat: ** Autoplay this card and ** refund its [E] cost.",
			"NAME": "Pandora's Actor"
		},
		"animator:Sebas":
		{
			"DESCRIPTION": "Deal damage equal to ** your [Block] to each enemy ** who intends to Attack. || When Discarded: ** Gain !M! [Temp HP].",
			"NAME": "Sebas"
		},
		"animator:Shalltear":
		{
			"DESCRIPTION": "Apply 1 [Weak] ** to ALL enemies. || Synergy: Steal 1 [F] ** from each enemy.",
			"NAME": "Shalltear"
		}
	},

	"SERIES:OWARINOSERAPH":
	{
		"animator:CrowleyEusford":
		{
			"DESCRIPTION": "Boost [F] [A]. || If you Exhausted ** a card this turn: ** Motivate 1.",
			"NAME": "Crowley Eusford"
		},
		"animator:FeridBathory":
		{
			"DESCRIPTION": "Whenever a card is ** Exhausted: Steal !M! HP from ** a random enemy as [Temp HP]. || <LIM>. At the start of turn, ** if you have 20 or more cards ** in Exhaust pile: Gain !S! [F].",
			"NAME": "Ferid Bathory"
		},
		"animator:Guren":
		{
			"DESCRIPTION": "Play the top !M! cards of ** your draw pile. Exhaust ** every Hindrance and ** {Attack} among them. || <SLM>. Gain 1 [Support Damage] for ** each card in Exhaust pile.",
			"NAME": "Guren"
		},
		"animator:HiiragiShinya":
		{
			"DESCRIPTION": "Fetch a card from your ** discard pile and Retain it, ** it costs 1 more this turn. || On Synergy: Gain !M! [Support Damage].",
			"NAME": "Shinya Hiiragi"
		},
		"animator:KrulTepes":
		{
			"DESCRIPTION": "Apply !M! [Weak]. || <LIM>. If this card ** kills an Elite or Boss: ** Obtain a {Blood Vial}.",
			"NAME": "Krul Tepes"
		},
		"animator:Mikaela":
		{
			"DESCRIPTION": "Exhaust a card in ** your discard pile. || If you Exhausted a ** Hindrance: Gain !S! [F].",
			"NAME": "Mikaela"
		},
		"animator:Mitsuba":
		{
			"DESCRIPTION": "If the enemy has more ** health than you, gain ** !S! additional [Block]. || When Exhausted: ** <DRW-M>.",
			"NAME": "Mitsuba"
		},
		"animator:Shigure":
		{
			"DESCRIPTION": "Apply !M! [Poison]. || <AS>: Cycle 1 card. || When Exhausted: ** Gain !S! [Support Damage].",
			"NAME": "Shigure"
		},
		"animator:Shinoa":
		{
			"DESCRIPTION": "Apply !M! [Vulnerable] ** to ALL enemies. || On Synergy, or when ** Exhausted: Apply !M! ** [Weak] to ALL enemies.",
			"NAME": "Shinoa"
		},
		"animator:Yoichi":
		{
			"DESCRIPTION": "Discard 1 card. ** Gain 1 [Support Damage]. || <slm>. Synergy: ** Activate your [Support Damage].",
			"NAME": "Yoichi"
		},
		"animator:Yuuichirou":
		{
			"DESCRIPTION": "<DRW>. || When Exhausted: ** Add {Asuramaru} to ** your discard pile.",
			"NAME": "Yuuichirou"
		}
	},

	"SERIES:TENSEISLIME":
	{
		"animator:Benimaru":
		{
			"DESCRIPTION": "Apply !M! [Burning]. || <SLM>. When ** Drawn: {Channel} 1 [Fire].",
			"NAME": "Benimaru"
		},
		"animator:GazelDwargon":
		{
			"DESCRIPTION": "Gain X [Plated Armor]. || At the start of turn: ** Maintain up to !M! [Block], ** multiplied by X.",
			"NAME": "Gazel Dwargon"
		},
		"animator:Hakurou":
		{
			"DESCRIPTION": "<FS>: Gain !S! [Block]. || On Synergy or when ** Drawn: Gain 1 [A].",
			"NAME": "Hakurou"
		},
		"animator:Kaijin":
		{
			"DESCRIPTION": "At the end of turn: Retain 1 ** card and increase its damage ** and [Block] by !M! this combat. || When you add this card ** to your deck: Permanently ** Upgrade a random Basic card. <SPACE>",
			"NAME": "Kaijin"
		},
		"animator:Millim":
		{
			"DESCRIPTION": "{~Unique}. ** Apply !M! [Burning] [Poison]. || Synergy: Draw 2 more ** cards next turn.",
			"NAME": "Millim"
		},
		"animator:Rimuru":
		{
			"DESCRIPTION": "Whenever you play a ** card: Turn this card ** into a copy of it.",
			"NAME": "Rimuru"
		},
		"animator:Shion":
		{
			"DESCRIPTION": "Discard 1 card. Next ** turn: <DRW>. || <LIM>. Synergy: ** Enter <FS>.",
			"NAME": "Shion"
		},
		"animator:Shizu":
		{
			"DESCRIPTION": "Whenever an {Attack} deals ** unblocked damage this ** combat: Apply 1 [Burning]. || Add a Burn to your ** discard pile.",
			"NAME": "Shizu"
		},
		"animator:Shuna":
		{
			"DESCRIPTION": "Gain 1 [B]. ** <DRW-M>. || When Drawn: ** Gain !S! [Temp HP].",
			"NAME": "Shuna"
		},
		"animator:Souei":
		{
			"DESCRIPTION": "Apply !M! [Poison]. || <slm>. Trigger the ** [Poison] of ALL enemies. ** If this kills an enemy: ** Gain 1 Intangible.",
			"NAME": "Souei"
		},
		"animator:Vesta":
		{
			"DESCRIPTION": "Research an {Elixir}. It ** will be completed ** after !M! turns.",
			"NAME": "Vesta"
		}
	},
	
	"AURA":
	{
		"animator:Enchantment1":
		{
			"DESCRIPTION": "Once per turn, ** pay !S! [E]: Choose and ** Enter any Stance.",
			"EXTENDED_DESCRIPTION": 
			[
				"Once per turn, pay !S! [E]: **  Choose and Enter any Stance, ** if you are already in the ** chosen Stance: Gain {0} [Block].",
				"Once per turn, pay !S! [E]: **  Choose and Enter any Stance, ** then Motivate the bottom ** card of your draw pile.",
				"Once per turn, pay !S! [E]  ** and lose {0} HP: Choose ** and Enter any Stance."
			],
			"NAME": "Stances"
		},
		"animator:Enchantment2":
		{
			"DESCRIPTION": "Once per turn, ** pay !S! [E]: {~Retain} ** all {[A-Gen] Powers} you ** gained this turn.",
			"EXTENDED_DESCRIPTION": 
			[
				"Once per turn, ** pay !S! [E]: Boost [F] ** and gain !M! [Plated Armor].",
				"Once per turn, ** pay !S! [E]: Boost [A] ** and Retain !M! card(s).",
				"Once per turn, ** pay !S! [E]: Boost [I] ** and gain !M! orb slot(s).",
				"Once per turn, ** pay !S! [E]: Boost [B] ** and gain !M! {Temp.} [Artifact].",
				"Once per turn, ** pay !S! [E]: Boost [C] and ** convert {0} HP to !M! [Temp HP]."
			],
			"NAME": "Powers"
		},
		"animator:Enchantment3":
		{
			"DESCRIPTION": "Once per turn, ** pay !S! [E]: Apply !M! [Vulnerable].",
			"EXTENDED_DESCRIPTION": 
			[
				"Once per turn, ** pay !S! [E]: Apply ** !M! [Vulnerable] and {0} [Poison].",
				"Once per turn, ** pay !S! [E]: Apply ** !M! [Vulnerable] and {0} [Weak].",
				"Once per turn, ** pay !S! [E] and lose ** {0} HP: Apply !M! [Vulnerable]."
			],
			"NAME": "Debuffs"
		}
	},

	"SPECIAL":
	{
		"animator:AffinityToken_Red":
		{
			"DESCRIPTION": "Gain +!M! <R> for ** the rest of combat. || !A! [{0}] or [{1}]: Gain [E].",
			"NAME": "Affinity Token"
		},
		"animator:AffinityToken_Green":
		{
			"DESCRIPTION": "Gain +!M! <G> for ** the rest of combat. || !A! [{0}] or [{1}]: Gain [E].",
			"NAME": "Affinity Token"
		},
		"animator:AffinityToken_Blue":
		{
			"DESCRIPTION": "Gain +!M! <B> for ** the rest of combat. || !A! [{0}] or [{1}]: Gain [E].",
			"NAME": "Affinity Token"
		},
		"animator:AffinityToken_Light":
		{
			"DESCRIPTION": "Gain +!M! <L> for ** the rest of combat. || !A! [{0}] or [{1}]: Gain [E].",
			"NAME": "Affinity Token"
		},		
		"animator:AffinityToken_Dark":
		{
			"DESCRIPTION": "Gain +!M! <D> for ** the rest of combat. || !A! [{0}] or [{1}]: Gain [E].",
			"NAME": "Affinity Token"
		},
		"animator:AffinityToken_General":
		{
			"DESCRIPTION": "When you add this card ** to your deck: Transform ** this card into an {Affinity ** Token} of your choice.",
			"NAME": "Affinity Token"
		},
		
		"animator:Asuramaru":
		{
			"DESCRIPTION": "Gain !M! [F] [A] [I]. ** Gain 2 {Demon Form}. ** Add 2 {Wounds} to ** your hand.",
			"NAME": "Asuramaru"
		},
		"animator:Bienfu":
		{
			"DESCRIPTION": "Unplayable. || When Drawn: Boost [I]. || When Discarded: Return ** this to your draw pile.",
			"NAME": "Bienfu"
		},
		"animator:BlackLotus":
		{
			"DESCRIPTION": "{~Retain} [F] [A]. || <FS>: Gain !M! [Metallicize]. || <AS>: Gain !S! [Blur].",
			"NAME": "Black Lotus"
		},
		"animator:ChlammyZell_Scheme":
		{
			"DESCRIPTION": "Whenever you play ** alternating card types ** this turn: Cycle 1 card ** and deal !M! damage to ** ALL enemies.",
			"NAME": "Scheme"
		},
		"animator:Darkness_Adrenaline":
		{
			"DESCRIPTION": "Gain [E]. ** <DRW-M>.",
			"NAME": "Adrenaline",
			"UPGRADE_DESCRIPTION": "Gain [E] [E]. ** <DRW-M>."
		},
		"animator:ElricAlphonse_Alt":
		{
			"DESCRIPTION": "Gain 1 orb slot. ** Channel !S! [Lightning]. || Synergy: Gain !M! [Plated Armor].",
			"NAME": "Armored Alphonse"
		},
		"animator:EntouJyuu":
		{
			"DESCRIPTION": "Gain !M! [A]. || Whenever you deal ** unblocked damage: ** Apply 1 [Burning].",
			"NAME": "Entou Jyuu"
		},
		"animator:Excalibur":
		{
			"DESCRIPTION": "Gain 1 Intangible.",
			"NAME": "Excalibur"
		},
		"animator:GiftBox":
		{
			"DESCRIPTION": "Discard all cards. || Add !M! random card(s) ** to your hand. || When Exhausted: Add !S! random cards to your draw pile.",
			"NAME": "Gift Box"
		},
		"animator:HinaKagiyama":
		{
			"DESCRIPTION": "Once per turn, when you ** draw a Curse: <DRW-M>. || At the start of turn: You may ** Purge a Hindrance in Exhaust ** pile to obtain a {Miracle}.",
			"EXTENDED_DESCRIPTION": ["The next #b{0} time(s) you draw a curse this turn, draw #b{1} cards.", "Choose up to {0} card(s) to Purge."],
			"NAME": "Hina Kagiyama"
		},
		"animator:HinaKagiyama_Miracle":
		{
			"DESCRIPTION": "Gain {+[E] }[E].",
			"NAME": "Miracle"
		},
		"animator:IchigoBankai":
		{
			"DESCRIPTION": "This card's damage ** is multiplied by X",
			"NAME": "Ichigo Bankai"
		},
		"animator:ImperialArchers":
		{
			"DESCRIPTION": "Gain !M! [Support Damage]. || When drawn: Deal !S! ** damage to a random ** enemy 3 times.",
			"NAME": "Imperial Archers"
		},
		"animator:Melzalgald_1":
		{
			"DESCRIPTION": "Gain !M! [F].",
			"NAME": "Melzalgald"
		},
		"animator:Melzalgald_2":
		{
			"DESCRIPTION": "Gain !M! [I].",
			"NAME": "Melzalgald"
		},
		"animator:Melzalgald_3":
		{
			"DESCRIPTION": "Gain !M! [A].",
			"NAME": "Melzalgald"
		},
		"animator:OrbCore_Aether":
		{
			"DESCRIPTION": "Channel !S! [Aether]. || On your second ** Synergy each turn: ** <DRW-M>, then ** discard 1 card.",
			"NAME": "Aether Core"
		},
		"animator:OrbCore_Chaos":
		{
			"DESCRIPTION": "Channel !S! [Chaos]. || On your second ** Synergy each turn: ** Choose 1 of 3 cards to ** obtain, it costs 1 less.",
			"NAME": "Chaos Core"
		},
		"animator:OrbCore_Dark":
		{
			"DESCRIPTION": "Channel !S! [Dark]. || On your second ** Synergy each turn: ** Apply !M! [Vulnerable] and !M! [Weak] to a random enemy.",
			"NAME": "Dark Core"
		},
		"animator:OrbCore_Fire":
		{
			"DESCRIPTION": "Channel !S! [Fire]. || On your second ** Synergy each turn: ** Apply !M! [Burning] to ** ALL enemies.",
			"NAME": "Fire Core"
		},
		"animator:OrbCore_Frost":
		{
			"DESCRIPTION": "Channel !S! [Frost]. || On your second ** Synergy each turn: ** Gain !M! [Plated Armor].",
			"NAME": "Frost Core"
		},
		"animator:OrbCore_Lightning":
		{
			"DESCRIPTION": "Channel !S! [Lightning]. || On your second ** Synergy each turn: ** Deal !M! damage ** to ALL enemies.",
			"NAME": "Lightning Core"
		},
		"animator:OrbCore_Plasma":
		{
			"DESCRIPTION": "Channel !S! [Plasma]. || On your second ** Synergy each turn: ** Gain !M! [Temp HP].",
			"NAME": "Plasma Core"
		},
		"animator:Respite":
		{
			"DESCRIPTION": "Delay certain ** doom by 1 turn.",
			"NAME": "Respite"
		},
		"animator:Shichika_Kyotouryuu":
		{
			"DESCRIPTION": "Remove the ** enemy's [Block].",
			"NAME": "Kyotouryuu"
		},
		"animator:ShinjiMatou_CommandSpell":
		{
			"DESCRIPTION": "Lose 1 orb slot to ** Fetch a <R> or <G> card ** from your discard pile, ** Motivate it and increase ** its scalings by !M!.",
			"NAME": "Command Spell"
		},
		"animator:Soujiro_Isami":
		{
			"DESCRIPTION": "<ST>: Boost [A].",
			"NAME": "Isami"
		},
		"animator:Soujiro_Kawara":
		{
			"DESCRIPTION": "If the enemy ** is attacking: Gain !M! ** additional [Block].",
			"NAME": "Kawara"
		},
		"animator:Soujiro_Hisako":
		{
			"DESCRIPTION": "Evoke your first ** orb to Boost [I].",
			"NAME": "Hisako"
		},
		"animator:Soujiro_Nazuna":
		{
			"DESCRIPTION": "Draw 1 less ** card next turn.",
			"NAME": "Nazuna"
		},
		"animator:TanyaDegurechaff_Type95":
		{
			"DESCRIPTION": "Channel 1 [Plasma]. || When Discarded or ** Drawn: Decrease this ** card's cost by 1 ** until played.",
			"NAME": "Type 95"
		},
		"animator:ThrowingKnife":
		{
			"DESCRIPTION": "{0} || When Discarded: ** Play this card on a ** random enemy.",
			"EXTENDED_DESCRIPTION": ["Apply a Debuff.", "Apply !M! [Weak].", "Apply !M! [Vulnerable].", "Apply !S! [Poison]."],
			"NAME": "Throwing-Knife"
		},
		"animator:Vesta_Elixir":
		{
			"DESCRIPTION": "Choose and combine ** up to 3 effects.",
			"EXTENDED_DESCRIPTION": ["Takes 1 less turn ** to complete."],
			"NAME": "Elixir"
		},
		"animator:Yusarin":
		{
			"DESCRIPTION": "Motivate !M!.",
			"NAME": "Yusarin"
		}
	},

	"STATUS":
	{
		"animator:Crystallize":
		{
			"DESCRIPTION": "Lose !S! HP twice. || Gain !M! [Metallicize] and 1 [C].",
			"NAME": "Crystallize"
		},
		"animator:GoblinChampion":
		{
			"DESCRIPTION": "At the end of ** your turn: Shuffle 1 ** random Goblin into ** your draw pile.",
			"NAME": "Goblin Champion"
		},
		"animator:GoblinKing":
		{
			"DESCRIPTION": "At the end of ** your turn: Shuffle 3 ** random Goblins into ** your draw pile.",
			"NAME": "Goblin King"
		},
		"animator:GoblinShaman":
		{
			"DESCRIPTION": "When you draw this, ** draw another card. At ** the end of your turn: ** Gain 1 Frail.",
			"NAME": "Goblin Shaman"
		},
		"animator:GoblinSoldier":
		{
			"DESCRIPTION": "When you draw this, ** draw another card. At ** the end of your turn: ** Take 2 damage.",
			"NAME": "Goblin Soldier"
		},
		"animator:Hans_Slimed":
		{
			"DESCRIPTION": "",
			"NAME": "Slimed",
			"UPGRADE_DESCRIPTION": "<DRW>"
		},
		"animator:Overheat":
		{
			"DESCRIPTION": "Draw 2 cards. ** Take !M! damage. ** ALL copies of this ** card gain 1 damage ** this combat.",
			"NAME": "Overheat"
		},
		"animator:TheHaunt":
		{
			"DESCRIPTION": "Gain !M! [Gold]. ** Become more haunted.",
			"NAME": "The Haunt"
		}
	},

	"ULTRARARE":
	{
		"animator:Azriel":
		{
			"DESCRIPTION": "Gain 2 Flight. || Whenever you apply ** a {Debuff}: Randomly ** Boost [F], [A] or [I].",
			"NAME": "Azriel"
		},
		"animator:Chomusuke":
		{
			"DESCRIPTION": "<DRW>. || <SLM>. When ** Exhausted: Return this ** card to your hand and ** gain [E] [E]",
			"NAME": "Chomusuke"
		},
		"animator:Cthulhu":
		{
			"DESCRIPTION": "This card's cost cannot ** be reduced, except by ** its own effect. || When Drawn: Add ** {Madness} to your hand.",
			"NAME": "Cthulhu"
		},
		"animator:Giselle":
		{
			"DESCRIPTION": "Apply !M! [Burning] ** to ALL enemies. || At the start of each ** combat: Channel 1 [Fire].",
			"NAME": "Giselle"
		},
		"animator:Hero":
		{
			"DESCRIPTION": "<DRW-M>. || <LIM>. If this card kills ** an enemy, 40% chance to ** obtain a {Relic} at the ** end of combat.",
			"NAME": "'Hero'"
		},
		"animator:HiiragiTenri":
		{
			"DESCRIPTION": "Play and Exhaust ALL cards ** in your discard pile. || <LIM>. When Exhausted: ** Shuffle your Exhaust pile ** into your draw pile.",
			"NAME": "Tenri Hiiragi"
		},
		"animator:HolyGrail":
		{
			"DESCRIPTION": "<DRW-M>. ** Refill your Energy. ** Lose !S! Max HP. || If you end the combat ** with this card in hand: ** Gain 2 Max HP.",
			"NAME": "The Grail"
		},
		"animator:JeanneDArc":
		{
			"DESCRIPTION": "Boost [B]. Purge a random ** Hindrance from anywhere. || At the start of combat: ** Gain !M! [Temp HP] and 1 [Artifact].",
			"NAME": "Jeanne D'Arc"
		},
		"animator:Kanami":
		{
			"DESCRIPTION": "Apply !M! [Vulnerable] to ALL ** enemies. Return this ** card to your draw pile. || Cooldown !S!: Change ** this card's form.",
			"NAME": "Kanami"
		},
		"animator:NivaLada":
		{
			"DESCRIPTION": "Cooldown !S! : ** Deal 300 damage. || Whenever you Exhaust or ** discard a card, reduce this ** card's Cooldown by 1.",
			"NAME": "Niva Lada"
		},
		"animator:Rose":
		{
			"DESCRIPTION": "<DRW-M>. Reload: ** Attack 1 additional time. || If this card kills an ** enemy, deal !S! damage ** to ALL enemies.",
			"NAME": "Rose"
		},
		"animator:SeriousSaitama":
		{
			"DESCRIPTION": "Stun ALL enemies. || Gain X [F]. Apply ** X [Vulnerable] to ALL enemies.",
			"NAME": "Serious Saitama",
			"UPGRADE_DESCRIPTION": "Stun ALL enemies. || Gain X+!M! [F]. Apply ** X+!M! [Vulnerable] to ALL enemies."
		},
		"animator:ShikizakiKiki":
		{
			"DESCRIPTION": "<DRW-M>. || Increase the [F] and [A] ** scaling of ALL {Attacks} ** in your hand by !S!.",
			"NAME": "Shikizaki Kiki"
		},
		"animator:SirTouchMe":
		{
			"DESCRIPTION": "Gain !M! Juggernaut. || At the start of ** combat: Gain !S! [Plated Armor].",
			"NAME": "Sir Touch Me"
		},
		"animator:SummoningRitual":
		{
			"DESCRIPTION": "Lose half your HP ** until end of combat. || Summon {Unnamed Doll}, ** it receives half of your ** unblocked damage.",
			"EXTENDED_DESCRIPTION": ["At the end of combat, recover #b{0} HP."],
			"NAME": "Summoning Ritual"
		},
		"animator:Truth":
		{
			"DESCRIPTION": "Gain !M! [F], [A], [I] and [E]. || If you have at least 3 ** unique orbs: Remove all your ** orbs. Otherwise choose and ** replace a card in your deck ** with a {~Wound}.",
			"NAME": "Truth"
		},
		"animator:Veldora":
		{
			"DESCRIPTION": "Gain !S! [I]. Evoke ** ALL orbs !M! times. || When Drawn: Channel ** 2 random orbs.",
			"NAME": "Veldora"
		},
		"animator:Walpurgisnacht":
		{
			"DESCRIPTION": "Add !M! random Spellcaster(s) ** to your hand. They cost 0 ** this turn. || At start of turn: Evoke your ** next orb for each Curse and ** Spellcaster in your hand.",
			"EXTENDED_DESCRIPTION": ["At the start of turn, #yEvoke your next orb once for each #yCurse plus each #ySpellcaster in your hand."],
			"NAME": "Walpurgisnacht"
		}
	}
}
